django_related_field_display-0.1.3.dist-info/licenses/LICENSE
related_field_display/__init__.py
related_field_display/admin.py
django_related_field_display-0.1.3.dist-info/METADATA
django_related_field_display-0.1.3.dist-info/WHEEL
django_related_field_display-0.1.3.dist-info/top_level.txt
django_related_field_display-0.1.3.dist-info/RECORD
