Metadata-Version: 2.4
Name: django-related-field-display
Version: 0.1.3
Summary: A Django admin mixin for displaying related fields with clickable links.
Home-page: https://github.com/natgho/django-related-field-display
Author: Sezer Bozkir
Author-email: admin@sezerbozkir.com
Classifier: Framework :: Django
Classifier: Programming Language :: Python :: 3
Classifier: License :: OSI Approved :: MIT License
Requires-Python: >=3.9
License-File: LICENSE
Requires-Dist: Django>=3.2
Dynamic: author
Dynamic: author-email
Dynamic: classifier
Dynamic: description
Dynamic: description-content-type
Dynamic: home-page
Dynamic: license-file
Dynamic: requires-dist
Dynamic: requires-python
Dynamic: summary
